Metadata-Version: 1.0
Name: fodio
Version: 1.0.1
Summary: A scraping library made to be simple and asynchronous
Home-page: https://github.com/Zwork101/fodio
Author: Nathan Zilora
Author-email: zwork101@gmail.com
License: Apache2
Platform: UNKNOWN
